orthauth/__init__.py
orthauth/core.py
orthauth/exceptions.py
orthauth/stores.py
orthauth/utils.py
orthauth-0.0.19.dist-info/licenses/LICENSE
orthauth-0.0.19.dist-info/METADATA
orthauth-0.0.19.dist-info/WHEEL
orthauth-0.0.19.dist-info/top_level.txt
orthauth-0.0.19.dist-info/RECORD
