Metadata-Version: 2.4
Name: orthauth
Version: 0.0.19
Summary: A library to separate configuration and authentication from program logic
Home-page: https://github.com/tgbugs/orthauth
Author: Tom Gillespie
Author-email: tgbugs@gmail.com
License: MIT
Keywords: python orthogonal authentication config configuration management
Classifier: Development Status :: 4 - Beta
Classifier: License :: OSI Approved :: MIT License
Classifier: Programming Language :: Python :: 3.7
Classifier: Programming Language :: Python :: 3.8
Classifier: Programming Language :: Python :: 3.9
Classifier: Programming Language :: Python :: 3.10
Classifier: Programming Language :: Python :: 3.11
Classifier: Programming Language :: Python :: 3.12
Classifier: Programming Language :: Python :: 3.13
Classifier: Programming Language :: Python :: Implementation :: CPython
Classifier: Programming Language :: Python :: Implementation :: PyPy
Classifier: Operating System :: POSIX :: Linux
Classifier: Operating System :: MacOS :: MacOS X
Classifier: Operating System :: Microsoft :: Windows
Requires-Python: >=3.7
License-File: LICENSE
Provides-Extra: test
Requires-Dist: pytest; extra == "test"
Requires-Dist: pyyaml; extra == "test"
Requires-Dist: sxpyr>=0.0.2; extra == "test"
Provides-Extra: yaml
Requires-Dist: pyyaml; extra == "yaml"
Provides-Extra: sxpr
Requires-Dist: sxpyr>=0.0.2; extra == "sxpr"
Dynamic: author
Dynamic: author-email
Dynamic: classifier
Dynamic: description
Dynamic: description-content-type
Dynamic: home-page
Dynamic: keywords
Dynamic: license
Dynamic: license-file
Dynamic: provides-extra
Dynamic: requires-python
Dynamic: summary
